{"attempt":1,"conclusion":"success","createdAt":"2025-01-23T10:49:36Z","databaseId":12927585251,"displayTitle":"[Ka0S] Uploading resume execution files to the repository...","event":"push","headBranch":"H633-modulo-de-execution","headSha":"3d83b17302375d8c4feb92a5602e1c8e61de2e68","jobs":[{"completedAt":"2025-01-23T10:50:29Z","conclusion":"skipped","databaseId":36053064093,"name":"job-core","startedAt":"2025-01-23T10:50:29Z","status":"completed","steps":[],"url":"https://github.com/SantaKa0S/kaos/actions/runs/12927585251/job/36053064093"},{"completedAt":"2025-01-23T10:50:30Z","conclusion":"skipped","databaseId":36053065142,"name":"job-compliance","startedAt":"2025-01-23T10:50:30Z","status":"completed","steps":[],"url":"https://github.com/SantaKa0S/kaos/actions/runs/12927585251/job/36053065142"},{"completedAt":"2025-01-23T10:50:30Z","conclusion":"skipped","databaseId":36053065560,"name":"job-observability","startedAt":"2025-01-23T10:50:30Z","status":"completed","steps":[],"url":"https://github.com/SantaKa0S/kaos/actions/runs/12927585251/job/36053065560"},{"completedAt":"2025-01-23T10:50:31Z","conclusion":"skipped","databaseId":36053066045,"name":"job-security","startedAt":"2025-01-23T10:50:31Z","status":"completed","steps":[],"url":"https://github.com/SantaKa0S/kaos/actions/runs/12927585251/job/36053066045"},{"completedAt":"2025-01-23T10:50:31Z","conclusion":"skipped","databaseId":36053066446,"name":"job-codescan","startedAt":"2025-01-23T10:50:31Z","status":"completed","steps":[],"url":"https://github.com/SantaKa0S/kaos/actions/runs/12927585251/job/36053066446"},{"completedAt":"2025-01-23T10:50:31Z","conclusion":"skipped","databaseId":36053066832,"name":"job-flows","startedAt":"2025-01-23T10:50:31Z","status":"completed","steps":[],"url":"https://github.com/SantaKa0S/kaos/actions/runs/12927585251/job/36053066832"},{"completedAt":"2025-01-23T10:50:32Z","conclusion":"skipped","databaseId":36053067424,"name":"handle_failure","startedAt":"2025-01-23T10:50:32Z","status":"completed","steps":[],"url":"https://github.com/SantaKa0S/kaos/actions/runs/12927585251/job/36053067424"},{"completedAt":"2025-01-23T10:50:33Z","conclusion":"skipped","databaseId":36053067866,"name":"handle-success","startedAt":"2025-01-23T10:50:33Z","status":"completed","steps":[],"url":"https://github.com/SantaKa0S/kaos/actions/runs/12927585251/job/36053067866"},{"completedAt":"2025-01-23T10:50:44Z","conclusion":"success","databaseId":36053068208,"name":"end-workflow","startedAt":"2025-01-23T10:50:39Z","status":"completed","steps":[{"completedAt":"2025-01-23T10:50:38Z","conclusion":"success","name":"Set up job","number":1,"startedAt":"2025-01-23T10:50:38Z","status":"completed"},{"completedAt":"2025-01-23T10:50:39Z","conclusion":"success","name":"Finaliza el workflow","number":2,"startedAt":"2025-01-23T10:50:39Z","status":"completed"},{"completedAt":"2025-01-23T10:50:39Z","conclusion":"success","name":"Complete job","number":3,"startedAt":"2025-01-23T10:50:39Z","status":"completed"}],"url":"https://github.com/SantaKa0S/kaos/actions/runs/12927585251/job/36053068208"}],"name":"Ka0S","number":686,"startedAt":"2025-01-23T10:49:36Z","status":"completed","updatedAt":"2025-01-23T10:50:46Z","url":"https://github.com/SantaKa0S/kaos/actions/runs/12927585251","workflowDatabaseId":130536173,"workflowName":"Ka0S"}
